pydbx_hng/models/base/base_model.py
pydbx_hng-2.0.3.dist-info/METADATA
pydbx_hng-2.0.3.dist-info/WHEEL
pydbx_hng-2.0.3.dist-info/top_level.txt
pydbx_hng-2.0.3.dist-info/RECORD
