Metadata-Version: 2.4
Name: pydbx-hng
Version: 2.0.3
Summary: A contract-driven Python toolkit for structured, explicit, and predictable database operations.
Author-email: kaioman <kajin0318@gmail.com>
Project-URL: Homepage, https://github.com/kaioman/pydbx-hng
Project-URL: Repository, https://github.com/kaioman/pydbx-hng
Project-URL: Issues, https://github.com/kaioman/pydbx-hng/issues
Requires-Dist: sqlalchemy
